odoo/addons/l10n_br_nfe_spec/README.rst
odoo/addons/l10n_br_nfe_spec/__init__.py
odoo/addons/l10n_br_nfe_spec/__manifest__.py
odoo/addons/l10n_br_nfe_spec/i18n/l10n_br_nfe_spec.pot
odoo/addons/l10n_br_nfe_spec/models/__init__.py
odoo/addons/l10n_br_nfe_spec/models/spec_models.py
odoo/addons/l10n_br_nfe_spec/models/v4_00/__init__.py
odoo/addons/l10n_br_nfe_spec/models/v4_00/leiauteNFe.py
odoo/addons/l10n_br_nfe_spec/readme/CONFIGURE.rst
odoo/addons/l10n_br_nfe_spec/readme/CONTRIBUTORS.rst
odoo/addons/l10n_br_nfe_spec/readme/DESCRIPTION.rst
odoo/addons/l10n_br_nfe_spec/readme/INSTALL.rst
odoo/addons/l10n_br_nfe_spec/readme/ROADMAP.rst
odoo/addons/l10n_br_nfe_spec/readme/USAGE.rst
odoo/addons/l10n_br_nfe_spec/static/description/icon.png
odoo/addons/l10n_br_nfe_spec/static/description/index.html
odoo/addons/l10n_br_nfe_spec/tests/__init__.py
odoo/addons/l10n_br_nfe_spec/tests/test_nfe_import.py
odoo13_addon_l10n_br_nfe_spec-13.0.1.0.1.dev4.dist-info/METADATA
odoo13_addon_l10n_br_nfe_spec-13.0.1.0.1.dev4.dist-info/WHEEL
odoo13_addon_l10n_br_nfe_spec-13.0.1.0.1.dev4.dist-info/top_level.txt
odoo13_addon_l10n_br_nfe_spec-13.0.1.0.1.dev4.dist-info/RECORD
